jp_range/__init__.py
jp_range/interval.py
jp_range/parser.py
jp_range/py.typed
jp_range-0.4.2.dist-info/METADATA
jp_range-0.4.2.dist-info/WHEEL
jp_range-0.4.2.dist-info/RECORD
