Metadata-Version: 2.4
Name: jp-range
Version: 0.4.2
Summary: Utilities for parsing Japanese numeric ranges.
Author-email: neka-nat <nekanat.stock@gmail.com>
Requires-Python: >=3.12
Requires-Dist: neologdn>=0.5.4
Requires-Dist: pandas>=2.2.3
Requires-Dist: pydantic>=2.0
Provides-Extra: excel
Requires-Dist: openpyxl>=3.1.5; extra == 'excel'
